zigbee2mqtt/__init__.py
zigbee2mqtt/exceptions.py
zigbee2mqtt/py.typed
zigbee2mqtt/zigbee2mqtt.py
zigbee2mqtt-0.0.1.dist-info/LICENSE.md
zigbee2mqtt-0.0.1.dist-info/WHEEL
zigbee2mqtt-0.0.1.dist-info/METADATA
zigbee2mqtt-0.0.1.dist-info/RECORD
