Metadata-Version: 2.1
Name: zigbee2mqtt
Version: 0.0.1
Summary: Python client for Zigbee2MQTT.
Home-page: https://github.com/frenck/python-zigbee2mqtt
License: MIT
Keywords: zigbee,zigbee2mqtt,z2m,mqtt,client
Author: Franck Nijhof
Author-email: opensource@frenck.dev
Maintainer: Franck Nijhof
Maintainer-email: opensource@frenck.dev
Requires-Python: >=3.8,<4.0
Classifier: Development Status :: 1 - Planning
Classifier: Intended Audience :: Developers
Classifier: License :: OSI Approved :: MIT License
Classifier: Natural Language :: English
Classifier: Programming Language :: Python :: 3
Classifier: Programming Language :: Python :: 3.10
Classifier: Programming Language :: Python :: 3.8
Classifier: Programming Language :: Python :: 3.9
Classifier: Topic :: Software Development :: Libraries :: Python Modules
Requires-Dist: pydantic (>=1.8.0,<2.0.0)
Project-URL: Bug Tracker, https://github.com/frenck/python-zigbee2mqtt/issues
Project-URL: Changelog, https://github.com/frenck/python-zigbee2mqtt/releases
Project-URL: Documentation, https://github.com/frenck/python-zigbee2mqtt
Project-URL: Repository, https://github.com/frenck/python-zigbee2mqtt
